{
  "snapshot_id": "20260522T2204",
  "timestamp": "2026-05-22T19:11:13.588Z",
  "label": "2026-05-22, 22:04",
  "total_participants": 0,
  "competition": "moex-ai-agent",
  "source": "github-actions",
  "benchmark": {
    "name": "IMOEX",
    "capital": 979005
  },
  "entries": [
    {
      "rank": 1,
      "team": "Команда",
      "captain": "vpack20",
      "capital": 1014605,
      "commission": 8074,
      "load_pct": 66,
      "days": 6,
      "trades": 423,
      "turnover": 16148162,
      "activity": "today"
    },
    {
      "rank": 2,
      "team": "Казанские Бедолаги",
      "captain": "kaifogradsky77",
      "capital": 1002576,
      "commission": 4037,
      "load_pct": 0,
      "days": 2,
      "trades": 25,
      "turnover": 8074134,
      "activity": "today"
    },
    {
      "rank": 3,
      "team": "Jarvis",
      "captain": "mail10102005",
      "capital": 1001301,
      "commission": 5042,
      "load_pct": 29,
      "days": 3,
      "trades": 45,
      "turnover": 10085118,
      "activity": "week"
    },
    {
      "rank": 4,
      "team": "Бу, испугался?",
      "captain": "Belkovskyy",
      "capital": 1000985,
      "commission": 1158,
      "load_pct": 0,
      "days": 3,
      "trades": 84,
      "turnover": 2316283,
      "activity": "today"
    },
    {
      "rank": 5,
      "team": "ОРЕХАБ",
      "captain": "ras0087",
      "capital": 1000013,
      "commission": 11,
      "load_pct": 0,
      "days": 2,
      "trades": 7,
      "turnover": 22070,
      "activity": "week"
    },
    {
      "rank": 6,
      "team": "Happiness Hedging Quants",
      "captain": "mkhmzr",
      "capital": 999998,
      "commission": 2,
      "load_pct": 0,
      "days": 1,
      "trades": 2,
      "turnover": 3448,
      "activity": "week"
    },
    {
      "rank": 7,
      "team": "Козырный Бутерброд",
      "captain": "nastyiam",
      "capital": 999944,
      "commission": 69,
      "load_pct": 0,
      "days": 1,
      "trades": 96,
      "turnover": 137428,
      "activity": "today"
    },
    {
      "rank": 8,
      "team": "Vortix",
      "captain": "temshik_trader",
      "capital": 999844,
      "commission": 6073,
      "load_pct": 1,
      "days": 4,
      "trades": 222,
      "turnover": 12146672,
      "activity": "today"
    },
    {
      "rank": 9,
      "team": "AllegroCode",
      "captain": "dgalimov560",
      "capital": 999631,
      "commission": 7278,
      "load_pct": 92,
      "days": 3,
      "trades": 577,
      "turnover": 14553509,
      "activity": "today"
    },
    {
      "rank": 10,
      "team": "SoloTech",
      "captain": "stasvinokur",
      "capital": 999153,
      "commission": 848,
      "load_pct": 6,
      "days": 6,
      "trades": 32,
      "turnover": 1695075,
      "activity": "today"
    },
    {
      "rank": 11,
      "team": "Дядя Стэн",
      "captain": "chaikinkv",
      "capital": 998949,
      "commission": 534,
      "load_pct": 4,
      "days": 1,
      "trades": 3,
      "turnover": 1067793,
      "activity": "week"
    },
    {
      "rank": 12,
      "team": "A-team",
      "captain": "liken17",
      "capital": 997672,
      "commission": 256,
      "load_pct": 27,
      "days": 3,
      "trades": 21,
      "turnover": 511228,
      "activity": "today"
    },
    {
      "rank": 13,
      "team": "Байкальск",
      "captain": "piledreke",
      "capital": 995777,
      "commission": 1599,
      "load_pct": 21,
      "days": 3,
      "trades": 38,
      "turnover": 3197872,
      "activity": "week"
    },
    {
      "rank": 14,
      "team": "LLMao",
      "captain": "pavel",
      "capital": 993532,
      "commission": 376,
      "load_pct": 74,
      "days": 2,
      "trades": 8,
      "turnover": 753144,
      "activity": "week"
    },
    {
      "rank": 15,
      "team": "solanaboys",
      "captain": "moexflipper",
      "capital": 993435,
      "commission": 2165,
      "load_pct": 0,
      "days": 3,
      "trades": 47,
      "turnover": 4329714,
      "activity": "today"
    },
    {
      "rank": 16,
      "team": "Profit",
      "captain": "picsile23",
      "capital": 990375,
      "commission": 2202,
      "load_pct": 77,
      "days": 1,
      "trades": 35,
      "turnover": 4403898,
      "activity": "today"
    },
    {
      "rank": 17,
      "team": "YA_week",
      "captain": "romalevints",
      "capital": 988996,
      "commission": 37787,
      "load_pct": 0,
      "days": 6,
      "trades": 1476,
      "turnover": 75573771,
      "activity": "today"
    },
    {
      "rank": 18,
      "team": "АБОБА",
      "captain": "serfetto",
      "capital": 988967,
      "commission": 5117,
      "load_pct": 97,
      "days": 7,
      "trades": 575,
      "turnover": 10233403,
      "activity": "today"
    },
    {
      "rank": 19,
      "team": "AI Portfolio Manager",
      "captain": "sergey-1221",
      "capital": 987415,
      "commission": 488,
      "load_pct": 96,
      "days": 1,
      "trades": 3,
      "turnover": 976734,
      "activity": "today"
    },
    {
      "rank": 20,
      "team": "Jevio Team",
      "captain": "klevin3701",
      "capital": 987144,
      "commission": 7599,
      "load_pct": 0,
      "days": 2,
      "trades": 174,
      "turnover": 15198532,
      "activity": "ago"
    },
    {
      "rank": 21,
      "team": "AITraiding",
      "captain": "a.strachenkov",
      "capital": 986373,
      "commission": 20887,
      "load_pct": 74,
      "days": 9,
      "trades": 718,
      "turnover": 41772956,
      "activity": "today"
    },
    {
      "rank": 22,
      "team": "pacemaker",
      "captain": "tialgo",
      "capital": 986372,
      "commission": 1247,
      "load_pct": 48,
      "days": 2,
      "trades": 11,
      "turnover": 2494455,
      "activity": "today"
    },
    {
      "rank": 23,
      "team": "ThisIsMISIS",
      "captain": "trader228",
      "capital": 984893,
      "commission": 7963,
      "load_pct": 0,
      "days": 5,
      "trades": 467,
      "turnover": 15925248,
      "activity": "week"
    },
    {
      "rank": 24,
      "team": "dodep MISIS",
      "captain": "and159753000000000000000000",
      "capital": 981408,
      "commission": 13037,
      "load_pct": 0,
      "days": 3,
      "trades": 220,
      "turnover": 26074053,
      "activity": "week"
    },
    {
      "rank": 25,
      "team": "Дети Баффета",
      "captain": "antsev.itmo",
      "capital": 974753,
      "commission": 29912,
      "load_pct": 77,
      "days": 4,
      "trades": 301,
      "turnover": 59678432,
      "activity": "today"
    },
    {
      "rank": 26,
      "team": "eveloup",
      "captain": "h.timur.alisherovich",
      "capital": 948830,
      "commission": 56927,
      "load_pct": 84,
      "days": 9,
      "trades": 1694,
      "turnover": 113853760,
      "activity": "today"
    },
    {
      "rank": 27,
      "team": "Golden Boys",
      "captain": "ivaldepabloadrian",
      "capital": 934671,
      "commission": 61702,
      "load_pct": 20,
      "days": 3,
      "trades": 1917,
      "turnover": 123163952,
      "activity": "today"
    }
  ]
}